easy_start_tiehu/__init__.py
easy_start_tiehu/pklot.py
easy_start_tiehu-0.1.2.dist-info/licenses/LICENSE
easy_start_tiehu-0.1.2.dist-info/METADATA
easy_start_tiehu-0.1.2.dist-info/WHEEL
easy_start_tiehu-0.1.2.dist-info/top_level.txt
easy_start_tiehu-0.1.2.dist-info/RECORD
